Workbook

Sheet README
B2: HOME COMPUTE NODE — WORK-PER-DOLLAR MODEL
B3: Single-socket AMD EPYC 9005 (Turin). Buy-vs-rent settled: buy. This picks the machine.
B5: HOW TO USE
B6: Blue cells | C6: Inputs and scenario levers. Edit these. Everything else is a formula.
B7: Yellow fill | C7: Key assumptions most likely to be wrong or to move. Check before committing money.
B8: Green text | C8: Pulled from another tab.
B9: Tab: Inputs | C9: Shared assumptions — electricity, hold period, utilization, RAM $/GB, PSU efficiency.
B10: Tab: Compare | C10: The four CPU candidates side by side. Row 37 is the answer.
B11: Tab: Parts List | C11: The BOM. Non-CPU parts are identical across all four candidates.
B12: Tab: Formula | C12: The model written out. Read this once.
B13: Tab: Sensitivity | C13: What would have to be true to change the answer.
B14: Tab: Rent Compare | C14: Hetzner, same metric.
B15: Tab: Sources | C15: Every number, where it came from, and how solid it is.
B17: THE ONE METRIC
B18: Psi = TCO / (W x U x Y) | C18: Dollars per SPECrate-point-year. All-in cost divided by throughput actually delivered. Lower wins.
C19: It folds capex, watts, utilization, cooling and hold period into one number you can rank on.
B21: WHAT THE MODEL SAYS
B22: Winner | C22: =CONCATENATE("EPYC ", INDEX(Compare!$C$3:$F$3, MATCH(MIN(Compare!$C$37:$F$37), Compare!$C$37:$F$37, 0)), " — ", TEXT(MIN(Compare!$C$37:$F$37),"$#,##0.00"), " per SPECrate-point-year") -> EPYC 9965 — $2.04 per SPECrate-point-year
B23: Best perf/watt | C23: =CONCATENATE("EPYC ", INDEX(Compare!$C$3:$F$3, MATCH(MAX(Compare!$C$38:$F$38), Compare!$C$38:$F$38, 0)), " — ", TEXT(MAX(Compare!$C$38:$F$38),"0.00"), " SPECrate points per wall watt") -> EPYC 9845 — 2.96 SPECrate points per wall watt
B25: CONFIDENCE
B26: Solid: 2-socket SPECrate scores (spec.org vendor submissions), CPU street prices, cTDP ranges, board specs.
B27: Estimated: 1-socket work rates (scaled from 2P by a factor calibrated on the 9745, where both are measured).
B28: Estimated: the 9965 derate at 450W. Phoronix measured the 9745 at 320W; nobody published 450-vs-500 on the 9965.
B29: Volatile: DDR5 RDIMM $/GB. Moving weekly. Re-check the day you buy.
B30: The ranking survives the estimates, because the 1P scaling factor is applied identically to every candidate.

Sheet Inputs
B2: SHARED INPUTS
B3: Blue = edit. These drive every tab.
B5: OPERATING
B6: Symbol | C6: Value | D6: Unit | E6: Note
B7: Y — hold period | C7: 10 | D7: years | E7: Turin shipped Oct-2024. 10 yr means running to 2036; 5 yr is the realistic economic life.
B8: U — utilization | C8: 1 | D8: fraction | E8: Share of wall-clock the box is actually loaded. 1.00 = your stated 24/7 plan.
B9: Hours per year | C9: 8766 | D9: h | E9: 365.25 x 24.
B10: r — electricity price | C10: 0.2 | D10: $/kWh | E10: BGE price-to-compare 14.6c generation-only; MD residential all-in averages 16-22c. 20c is fair-to-conservative.
B11: e — electricity escalation | C11: 0 | D11: %/yr | E11: MD rates rose ~3.8% YoY. Set 0.03 to see the escalated case. 0 reproduces the flat-rate numbers.
B12: d — discount rate | C12: 0 | D12: %/yr | E12: Set 0.08 to price $15k today against energy spread over a decade. 0 = nominal.
B14: SYSTEM
B15: P_plat — platform draw | C15: 100 | D15: W | E15: Board + 12 DIMMs + NVMe + fans + BMC. 12 DDR5 RDIMMs alone run ~50-70W loaded, so 100 is on the optimistic side.
B16: eta — PSU efficiency | C16: 0.92 | D16: fraction | E16: 80+ Titanium is ~94% at 50% load. 0.92 is conservative.
B17: k — cooling overhead | C17: 1 | D17: x | E17: 1.00 if the space is unconditioned. ~1.10 for a Maryland basement on AC in summer (COP~3), netted against the winter heating credit.
B18: P_idle — idle wall draw | C18: 120 | D18: W | E18: Only matters when U < 1.
B19: S — residual value at year Y | C19: 0 | D19: $ | E19: Conservative zero. Used EPYC holds value; set it if you plan to resell.
B21: MEMORY (the volatile line)
B22: DIMM slots populated | C22: 12 | D22: ea | E22: All 12 channels. Never populate fewer — bandwidth scales with channels.
B23: GB per DIMM | C23: 32 | D23: GB | E23: 32 gives 2GB/core on the 9965 and is dual-rank. 16 halves the cost but is single-rank x8 and gives up achieved bandwidth.
B24: DDR5-6400 RDIMM price | C24: 35.7 | D24: $/GB | E24: Observed band $29.56-$39.06/GB, median $35.70 (Aug-2026). RE-CHECK THE DAY YOU BUY.
B25: Total memory | C25: =$C$22*$C$23 -> 384 | D25: GB
B26: Memory cost | C26: =$C$22*$C$23*$C$24 -> 13708.8 | D26: $
B28: BENCHMARK CALIBRATION
B29: sigma — 1P scaling factor | C29: 0.5256 | D29: x | E29: Calibrated on the 9745, the only part with both published: 1P 1,230 / 2P 2,340 = 0.5256. Applied identically to all candidates, so it cancels out of the ranking.
B30: phi — derate at minimum cTDP | C30: 0.98 | D30: x | E30: Phoronix, 555-benchmark geomean: the 9745 at 320W cTDP delivered ~98% of its 400W performance. A 20% TDP cut for 2% throughput.
B32: DERIVED
B33: Energy year-factor | C33: =IF($C$11=0,$C$7,((1+$C$11)^$C$7-1)/$C$11) -> 10 | E33: Sum of (1+e)^t over the hold. Equals Y when escalation is zero.
B34: NPV year-factor | C34: =IF(ABS($C$11-$C$12)<0.0000001,$C$7,(1-((1+$C$11)/(1+$C$12))^$C$7)/(1-(1+$C$11)/(1+$C$12))) -> 10 | E34: Same series discounted at d. Equals the energy year-factor when d = 0.

Sheet Parts List
B2: PARTS LIST — SINGLE NODE
B3: Non-CPU parts are identical across all four CPU candidates, so they cancel out of the comparison. The CPU is the only variable.
B5: Item | C5: Spec | D5: Qty | E5: Unit $ | F5: Ext $ | G5: Status | H5: Note
B6: Motherboard | C6: Gigabyte MZ33-AR1 — SP5, E-ATX, 24x DDR5 RDIMM, cTDP to 500W, 4x PCIe5 x16, 2x 10GbE, IPMI | D6: 1 | E6: 900 | F6: =D6*E6 -> 900 | G6: Confirm | H6: Supports every candidate including the 500W parts. This is the board Phoronix benched the 9745 on. Phoronix put it near $700; eBay/Newegg run $1,000-1,250.
B7: CPU | C7: =CONCATENATE("AMD EPYC ", INDEX(Compare!$C$3:$F$3, MATCH(MIN(Compare!$C$37:$F$37), Compare!$C$37:$F$37,0)), " — run at ", TEXT(INDEX(Compare!$C$13:$F$13, MATCH(MIN(Compare!$C$37:$F$37), Compare!$C$37:$F$37,0)),"0"), "W cTDP") -> AMD EPYC 9965 — run at 450W cTDP | D7: 1 | E7: =INDEX(Compare!$C$28:$F$28, MATCH(MIN(Compare!$C$37:$F$37), Compare!$C$37:$F$37,0)) -> 7000 | F7: =D7*E7 -> 7000 | G7: Confirm | H7: Auto-selected as the lowest Psi on the Compare tab. Street prices move; re-quote before ordering.
B8: Memory | C8: DDR5-6400 RDIMM, 2Rx8, ECC Registered — Samsung/Hynix/Micron | D8: =Inputs!$C$22 -> 12 | E8: =Inputs!$C$23*Inputs!$C$24 -> 1142.4 | F8: =D8*E8 -> 13708.8 | G8: VOLATILE | H8: Driven by the Inputs tab. Dual-rank matters: every SPECrate result behind this model used 2Rx4 modules.
B9: Chassis | C9: 4U rackmount, SP5 clearance, front-to-back airflow | D9: 1 | E9: 350 | F9: =D9*E9 -> 350 | G9: Est | H9: Rosewill RSV-L4500 class or similar.
B10: PSU | C10: 1000W 80+ Titanium, single rail | D10: 1 | E10: 300 | F10: =D10*E10 -> 300 | G10: Est | H10: At ~598W wall the unit sits near 60% load — the peak-efficiency band.
B11: CPU cooler | C11: SP5 4U active tower or 360mm AIO rated 500W+ | D11: 1 | E11: 180 | F11: =D11*E11 -> 180 | G11: Est | H11: Must be rated above the cTDP you actually run.
B12: Boot / scratch | C12: 2TB NVMe PCIe Gen4 | D12: 1 | E12: 220 | F12: =D12*E12 -> 220 | G12: Est | H12: NAND is inflated alongside DRAM. Add bulk storage separately if jobs need it.
B13: Fans | C13: 4U high-static-pressure set | D13: 1 | E13: 80 | F13: =D13*E13 -> 80 | G13: Est
B14: Misc | C14: Rails, SATA/MCIO cables, thermal paste, IPMI cable | D14: 1 | E14: 70 | F14: =D14*E14 -> 70 | G14: Est
B15: Non-CPU subtotal | F15: =SUM(F6:F6)+SUM(F8:F14) -> 15808.8 | H15: Identical across all four CPU candidates. This is the figure the Compare tab pulls.
B16: TOTAL CAPEX — as configured | F16: =F15+F7 -> 22808.8 | H16: Non-CPU subtotal plus the winning CPU.
B18: NOT IN THIS BOM
B19: Network switch, UPS, rack, PDU — assumed already present in the lab.
B20: Bulk data storage beyond the 2TB scratch drive.
B21: Sales tax and shipping.
B22: Your time. A DIY SP5 build is a weekend if the BIOS cooperates and longer if it does not.

Sheet Compare
B2: CPU CANDIDATES — FULL MATH
B3: Metric | C3: 9965 | D3: 9845 | E3: 9755 | F3: 9745
B4: SPECIFICATION
B5: Cores | C5: 192 | D5: 160 | E5: 128 | F5: 128
B6: Architecture | C6: Zen 5c | D6: Zen 5c | E6: Zen 5 | F6: Zen 5c
B7: L3 cache (MB) | C7: 384 | D7: 320 | E7: 512 | F7: 256 | H7: The 9755 carries double the 9745 L3 — the only candidate with a cache-locality argument.
B8: Default TDP (W) | C8: 500 | D8: 390 | E8: 500 | F8: 400
B9: cTDP floor (W) | C9: 450 | D9: 320 | E9: 500 | F9: 320 | H9: The 9965 cannot go below 450W. The Zen 5c 400W parts floor at 320W.
B10: Memory bandwidth (GB/s) | C10: 614 | D10: 614 | E10: 614 | F10: 614 | H10: Identical 12-channel DDR5-6400 pipe on every candidate. More cores = less bandwidth per core.
B11: Bandwidth per core (GB/s) | C11: =C10/C5 -> 3.1979167 | D11: =D10/D5 -> 3.8375 | E11: =E10/E5 -> 4.796875 | F11: =F10/F5 -> 4.796875 | H11: The 9965 gets 3.2 GB/s/core vs 4.8 on the 128-core parts. Matters only if your jobs stream.
B12: RUN CONFIGURATION
B13: P_cpu — cTDP setting (W) | C13: 450 | D13: 320 | E13: 500 | F13: 320 | H13: Run every part at its floor. This is the single biggest efficiency lever and it is free.
B14: phi — derate factor | C14: 0.99 | D14: 0.98 | E14: 1 | F14: 0.98 | H14: 0.98 measured on the 9745 at 320W. 0.99 on the 9965 at 450W is an ESTIMATE — a 10% TDP cut vs the 20% Phoronix tested. 9755 runs stock.
B15: RAM per core (GB) | C15: =(Inputs!$C$22*Inputs!$C$23)/C5 -> 2 | D15: =(Inputs!$C$22*Inputs!$C$23)/D5 -> 2.4 | E15: =(Inputs!$C$22*Inputs!$C$23)/E5 -> 3 | F15: =(Inputs!$C$22*Inputs!$C$23)/F5 -> 3 | H15: At 12x32GB. Drop to 16GB modules and these halve.
B17: WORK RATE
B18: 2P SPECrate2017_int_base | C18: 3140 | D18: 2620 | E18: 2589 | F18: 2330 | H18: MEASURED, spec.org vendor submissions. 9965 median of 4 results; 9845 single Dell result; 9745 median of 4; 9755 derived (see Sources) and the weakest of the four.
B19: sigma — 1P scaling factor | C19: =Inputs!$C$29 -> 0.5256 | D19: =Inputs!$C$29 -> 0.5256 | E19: =Inputs!$C$29 -> 0.5256 | F19: =Inputs!$C$29 -> 0.5256
B20: W — work rate (1P pts) | C20: =C18*C19*C14 -> 1633.8802 | D20: =D18*D19*D14 -> 1349.5306 | E20: =E18*E19*E14 -> 1360.7784 | F20: =F18*F19*F14 -> 1200.155 | H20: W = 2P score x sigma x phi. The 9745 lands at ~1,225 here against a measured 1P range of 1,170-1,270 — the scaling factor checks out.
B22: POWER
B23: P_wall — loaded draw (W) | C23: =(C13+Inputs!$C$15)/Inputs!$C$16 -> 597.82609 | D23: =(D13+Inputs!$C$15)/Inputs!$C$16 -> 456.52174 | E23: =(E13+Inputs!$C$15)/Inputs!$C$16 -> 652.17391 | F23: =(F13+Inputs!$C$15)/Inputs!$C$16 -> 456.52174 | H23: (P_cpu + platform) / PSU efficiency.
B24: P_eff — duty-weighted (W) | C24: =Inputs!$C$8*C23+(1-Inputs!$C$8)*Inputs!$C$18 -> 597.82609 | D24: =Inputs!$C$8*D23+(1-Inputs!$C$8)*Inputs!$C$18 -> 456.52174 | E24: =Inputs!$C$8*E23+(1-Inputs!$C$8)*Inputs!$C$18 -> 652.17391 | F24: =Inputs!$C$8*F23+(1-Inputs!$C$8)*Inputs!$C$18 -> 456.52174 | H24: Blends loaded and idle draw by utilization. Equals P_wall when U = 1.
B25: kWh per year | C25: =C24*Inputs!$C$17*Inputs!$C$9/1000 -> 5240.5435 | D25: =D24*Inputs!$C$17*Inputs!$C$9/1000 -> 4001.8696 | E25: =E24*Inputs!$C$17*Inputs!$C$9/1000 -> 5716.9565 | F25: =F24*Inputs!$C$17*Inputs!$C$9/1000 -> 4001.8696 | H25: Includes the cooling multiplier k.
B27: COST
B28: CPU street price | C28: 7000 | D28: 9684 | E28: 6500 | F28: 7200 | H28: New, US channel. The 9965 collapsed from its $14,813 launch MSRP; the 9845 never did, which is what costs it the win.
B29: Non-CPU capex | C29: ='Parts List'!$F$15 -> 15808.8 | D29: ='Parts List'!$F$15 -> 15808.8 | E29: ='Parts List'!$F$15 -> 15808.8 | F29: ='Parts List'!$F$15 -> 15808.8 | H29: Board, 12 DIMMs, chassis, PSU, cooler, NVMe. Identical for all four — it cancels out of the ranking.
B30: C — total capex | C30: =C28+C29 -> 22808.8 | D30: =D28+D29 -> 25492.8 | E30: =E28+E29 -> 22308.8 | F30: =F28+F29 -> 23008.8
B31: E — energy over hold | C31: =C25*Inputs!$C$10*Inputs!$C$33 -> 10481.087 | D31: =D25*Inputs!$C$10*Inputs!$C$33 -> 8003.7391 | E31: =E25*Inputs!$C$10*Inputs!$C$33 -> 11433.913 | F31: =F25*Inputs!$C$10*Inputs!$C$33 -> 8003.7391 | H31: kWh/yr x price x year-factor. Year-factor carries the escalation rate.
B32: S — residual value | C32: =Inputs!$C$19 -> 0 | D32: =Inputs!$C$19 -> 0 | E32: =Inputs!$C$19 -> 0 | F32: =Inputs!$C$19 -> 0
B33: TCO | C33: =C30+C31-C32 -> 33289.887 | D33: =D30+D31-D32 -> 33496.539 | E33: =E30+E31-E32 -> 33742.713 | F33: =F30+F31-F32 -> 31012.539
B35: RESULTS
B36: Work delivered (pt-years) | C36: =C20*Inputs!$C$8*Inputs!$C$7 -> 16338.802 | D36: =D20*Inputs!$C$8*Inputs!$C$7 -> 13495.306 | E36: =E20*Inputs!$C$8*Inputs!$C$7 -> 13607.784 | F36: =F20*Inputs!$C$8*Inputs!$C$7 -> 12001.55 | H36: W x U x Y.
B37: Psi — $ / SPECrate-pt-year | C37: =IF(C36=0,"",C33/C36) -> 2.0374742 | D37: =IF(D36=0,"",D33/D36) -> 2.4820882 | E37: =IF(E36=0,"",E33/E36) -> 2.4796626 | F37: =IF(F36=0,"",F33/F36) -> 2.5840444 | H37: THE ANSWER. Lowest wins.
B38: epsilon — pts per wall watt | C38: =IF(C23=0,"",C20/C23) -> 2.7330359 | D38: =IF(D23=0,"",D20/D23) -> 2.9561146 | E38: =IF(E23=0,"",E20/E23) -> 2.0865269 | F38: =IF(F23=0,"",F20/F23) -> 2.628911 | H38: Perf/watt. Note this ranks differently from Psi — efficiency and value are not the same question.
B39: theta — energy share of TCO | C39: =IF(C33=0,"",C31/C33) -> 0.31484297 | D39: =IF(D33=0,"",D31/D33) -> 0.23894227 | E39: =IF(E33=0,"",E31/E33) -> 0.33885577 | F39: =IF(F33=0,"",F31/F33) -> 0.25808074 | H39: How much of the ten-year bill is electricity rather than hardware.
B40: Rank by Psi | C40: =RANK(C37,$C$37:$F$37,1) -> 1 | D40: =RANK(D37,$C$37:$F$37,1) -> 3 | E40: =RANK(E37,$C$37:$F$37,1) -> 2 | F40: =RANK(F37,$C$37:$F$37,1) -> 4
B41: Penalty vs winner | C41: =IF(MIN($C$37:$F$37)=0,"",C37/MIN($C$37:$F$37)-1) -> 0 | D41: =IF(MIN($C$37:$F$37)=0,"",D37/MIN($C$37:$F$37)-1) -> 0.21821823 | E41: =IF(MIN($C$37:$F$37)=0,"",E37/MIN($C$37:$F$37)-1) -> 0.21702772 | F41: =IF(MIN($C$37:$F$37)=0,"",F37/MIN($C$37:$F$37)-1) -> 0.2682587 | H41: How much more you pay per unit of work by picking this instead of the winner.
B43: VERDICT | C43: =CONCATENATE("EPYC ", INDEX($C$3:$F$3, MATCH(MIN($C$37:$F$37),$C$37:$F$37,0)), " at ", TEXT(INDEX($C$13:$F$13, MATCH(MIN($C$37:$F$37),$C$37:$F$37,0)),"0"), "W cTDP — ", TEXT(MIN($C$37:$F$37),"$#,##0.00"), "/pt-yr, ", TEXT(INDEX($C$30:$F$30, MATCH(MIN($C$37:$F$37),$C$37:$F$37,0)),"$#,##0"), " capex") -> EPYC 9965 at 450W cTDP — $2.04/pt-yr, $22,809 capex

Sheet Formula
B2: THE MODEL
B3: Everything on the Compare tab is these eleven lines.
B5: Symbol | C5: Definition | D5: Meaning
B6: INPUTS — measured or quoted
B7: R2 | C7: 2-socket SPECrate2017_int_base | D7: Vendor-published throughput score. The only work number anyone actually measured.
B8: sigma | C8: 1P scaling factor: 0.5256 | D8: Converts a 2-socket score to 1-socket. Calibrated on the one part with both published.
B9: phi | C9: cTDP derate factor | D9: Throughput retained when you cap the part below its default TDP.
B10: P_cpu | C10: cTDP setting, watts | D10: What you set in BIOS.
B11: C_cpu | C11: CPU street price, $
B12: C_rest | C12: Non-CPU capex, $ | D12: Board, memory, chassis, PSU, cooling, disk.
B13: P_plat | C13: Platform draw, watts | D13: Everything on the board that is not the CPU.
B14: eta | C14: PSU efficiency, 0-1
B15: k | C15: Cooling overhead multiplier | D15: Watts of heat removal per watt of compute, plus 1.
B16: U | C16: Utilization, 0-1 | D16: Fraction of wall-clock actually doing work.
B17: P_idle | C17: Idle wall draw, watts
B18: r, e, d | C18: Electricity $/kWh, escalation, discount
B19: Y | C19: Hold period, years
B20: S | C20: Residual value at year Y, $
B22: DERIVED — in order
B23: 1 W | C23: = R2 x sigma x phi | D23: Work rate. Throughput this box sustains.
B24: 2 P_wall | C24: = (P_cpu + P_plat) / eta | D24: Wall draw under load.
B25: 3 P_eff | C25: = U x P_wall + (1-U) x P_idle | D25: Duty-cycle-weighted draw. Equals P_wall at full utilization.
B26: 4 kWh/yr | C26: = P_eff x k x 8766 / 1000 | D26: Annual energy, cooling included.
B27: 5 E | C27: = kWh/yr x r x [(1+e)^Y - 1] / e | D27: Energy cost over the hold. Reduces to kWh/yr x r x Y when e = 0.
B28: 6 C | C28: = C_cpu + C_rest | D28: Capex.
B29: 7 TCO | C29: = C + E - S | D29: All-in cost of ownership.
B30: 8 Work | C30: = W x U x Y | D30: Throughput actually delivered, in point-years.
B32: 9 PSI | C32: = TCO / Work | D32: DOLLARS PER SPECRATE-POINT-YEAR. Rank on this. Lower wins.
B34: 10 epsilon | C34: = W / P_wall | D34: Perf per wall watt. Efficiency, not value — it can rank differently from Psi.
B35: 11 theta | C35: = E / TCO | D35: Share of the bill that is electricity.
B36: 12 Psi_npv | C36: = [C + E_npv - S/(1+d)^Y] / Work | D36: Psi with future energy discounted to today. Set d on the Inputs tab.
B38: RENT COMPARISON
B39: 13 Psi_rent | C39: = (monthly x 12) / R_1P | D39: Same units. Directly comparable to Psi.
B40: 14 Ratio | C40: = Psi_rent / Psi | D40: How many times cheaper it is to own.
B42: WHY THIS METRIC AND NOT ANOTHER
B43: $/watt alone ignores that a box doing more work is worth more watts. It picks small, slow parts.
B44: Perf/watt alone ignores capex. It picks the 9845 here, which costs more per unit of work delivered.
B45: $/core is meaningless across architectures — a Zen 5c core and a Zen 5 core are not the same unit.
B46: PassMark saturates past roughly 100 cores and compresses the real gap. SPECrate does not. That is why it is gone.
B47: Psi is the only one that answers the actual question: what does a unit of sustained throughput cost me per year, all in.

Sheet Sensitivity
B2: SENSITIVITY — WHAT WOULD CHANGE THE ANSWER
B3: Each block recomputes Psi live from the Compare tab, varying one thing.
B5: A. ELECTRICITY PRICE ($/kWh)
B6: Psi at... | C6: 9965 | D6: 9845 | E6: 9755 | F6: 9745 | H6: The 9965 wins at every plausible power price. Its work advantage is too large to overcome with watts.
B7: 0.1 | C7: =(Compare!$C$30+Compare!$C$25*0.1*IF(Inputs!$C$11=0,Inputs!$C$7,((1+Inputs!$C$11)^Inputs!$C$7-1)/Inputs!$C$11)-Inputs!$C$19)/(Compare!$C$20*Inputs!$C$8*Inputs!$C$7) -> 1.716732 | D7: =(Compare!$D$30+Compare!$D$25*0.1*IF(Inputs!$C$11=0,Inputs!$C$7,((1+Inputs!$C$11)^Inputs!$C$7-1)/Inputs!$C$11)-Inputs!$C$19)/(Compare!$D$20*Inputs!$C$8*Inputs!$C$7) -> 2.1855503 | E7: =(Compare!$E$30+Compare!$E$25*0.1*IF(Inputs!$C$11=0,Inputs!$C$7,((1+Inputs!$C$11)^Inputs!$C$7-1)/Inputs!$C$11)-Inputs!$C$19)/(Compare!$E$20*Inputs!$C$8*Inputs!$C$7) -> 2.0595386 | F7: =(Compare!$F$30+Compare!$F$25*0.1*IF(Inputs!$C$11=0,Inputs!$C$7,((1+Inputs!$C$11)^Inputs!$C$7-1)/Inputs!$C$11)-Inputs!$C$19)/(Compare!$F$20*Inputs!$C$8*Inputs!$C$7) -> 2.2505984
B8: 0.2 | C8: =(Compare!$C$30+Compare!$C$25*0.2*IF(Inputs!$C$11=0,Inputs!$C$7,((1+Inputs!$C$11)^Inputs!$C$7-1)/Inputs!$C$11)-Inputs!$C$19)/(Compare!$C$20*Inputs!$C$8*Inputs!$C$7) -> 2.0374742 | D8: =(Compare!$D$30+Compare!$D$25*0.2*IF(Inputs!$C$11=0,Inputs!$C$7,((1+Inputs!$C$11)^Inputs!$C$7-1)/Inputs!$C$11)-Inputs!$C$19)/(Compare!$D$20*Inputs!$C$8*Inputs!$C$7) -> 2.4820882 | E8: =(Compare!$E$30+Compare!$E$25*0.2*IF(Inputs!$C$11=0,Inputs!$C$7,((1+Inputs!$C$11)^Inputs!$C$7-1)/Inputs!$C$11)-Inputs!$C$19)/(Compare!$E$20*Inputs!$C$8*Inputs!$C$7) -> 2.4796626 | F8: =(Compare!$F$30+Compare!$F$25*0.2*IF(Inputs!$C$11=0,Inputs!$C$7,((1+Inputs!$C$11)^Inputs!$C$7-1)/Inputs!$C$11)-Inputs!$C$19)/(Compare!$F$20*Inputs!$C$8*Inputs!$C$7) -> 2.5840444
B9: 0.3 | C9: =(Compare!$C$30+Compare!$C$25*0.3*IF(Inputs!$C$11=0,Inputs!$C$7,((1+Inputs!$C$11)^Inputs!$C$7-1)/Inputs!$C$11)-Inputs!$C$19)/(Compare!$C$20*Inputs!$C$8*Inputs!$C$7) -> 2.3582164 | D9: =(Compare!$D$30+Compare!$D$25*0.3*IF(Inputs!$C$11=0,Inputs!$C$7,((1+Inputs!$C$11)^Inputs!$C$7-1)/Inputs!$C$11)-Inputs!$C$19)/(Compare!$D$20*Inputs!$C$8*Inputs!$C$7) -> 2.7786261 | E9: =(Compare!$E$30+Compare!$E$25*0.3*IF(Inputs!$C$11=0,Inputs!$C$7,((1+Inputs!$C$11)^Inputs!$C$7-1)/Inputs!$C$11)-Inputs!$C$19)/(Compare!$E$20*Inputs!$C$8*Inputs!$C$7) -> 2.8997866 | F9: =(Compare!$F$30+Compare!$F$25*0.3*IF(Inputs!$C$11=0,Inputs!$C$7,((1+Inputs!$C$11)^Inputs!$C$7-1)/Inputs!$C$11)-Inputs!$C$19)/(Compare!$F$20*Inputs!$C$8*Inputs!$C$7) -> 2.9174905
B10: 0.4 | C10: =(Compare!$C$30+Compare!$C$25*0.4*IF(Inputs!$C$11=0,Inputs!$C$7,((1+Inputs!$C$11)^Inputs!$C$7-1)/Inputs!$C$11)-Inputs!$C$19)/(Compare!$C$20*Inputs!$C$8*Inputs!$C$7) -> 2.6789587 | D10: =(Compare!$D$30+Compare!$D$25*0.4*IF(Inputs!$C$11=0,Inputs!$C$7,((1+Inputs!$C$11)^Inputs!$C$7-1)/Inputs!$C$11)-Inputs!$C$19)/(Compare!$D$20*Inputs!$C$8*Inputs!$C$7) -> 3.075164 | E10: =(Compare!$E$30+Compare!$E$25*0.4*IF(Inputs!$C$11=0,Inputs!$C$7,((1+Inputs!$C$11)^Inputs!$C$7-1)/Inputs!$C$11)-Inputs!$C$19)/(Compare!$E$20*Inputs!$C$8*Inputs!$C$7) -> 3.3199106 | F10: =(Compare!$F$30+Compare!$F$25*0.4*IF(Inputs!$C$11=0,Inputs!$C$7,((1+Inputs!$C$11)^Inputs!$C$7-1)/Inputs!$C$11)-Inputs!$C$19)/(Compare!$F$20*Inputs!$C$8*Inputs!$C$7) -> 3.2509365
B11: 0.6 | C11: =(Compare!$C$30+Compare!$C$25*0.6*IF(Inputs!$C$11=0,Inputs!$C$7,((1+Inputs!$C$11)^Inputs!$C$7-1)/Inputs!$C$11)-Inputs!$C$19)/(Compare!$C$20*Inputs!$C$8*Inputs!$C$7) -> 3.3204431 | D11: =(Compare!$D$30+Compare!$D$25*0.6*IF(Inputs!$C$11=0,Inputs!$C$7,((1+Inputs!$C$11)^Inputs!$C$7-1)/Inputs!$C$11)-Inputs!$C$19)/(Compare!$D$20*Inputs!$C$8*Inputs!$C$7) -> 3.6682398 | E11: =(Compare!$E$30+Compare!$E$25*0.6*IF(Inputs!$C$11=0,Inputs!$C$7,((1+Inputs!$C$11)^Inputs!$C$7-1)/Inputs!$C$11)-Inputs!$C$19)/(Compare!$E$20*Inputs!$C$8*Inputs!$C$7) -> 4.1601586 | F11: =(Compare!$F$30+Compare!$F$25*0.6*IF(Inputs!$C$11=0,Inputs!$C$7,((1+Inputs!$C$11)^Inputs!$C$7-1)/Inputs!$C$11)-Inputs!$C$19)/(Compare!$F$20*Inputs!$C$8*Inputs!$C$7) -> 3.9178286
B13: B. HOLD PERIOD (years)
B14: Psi at... | C14: 9965 | D14: 9845 | E14: 9755 | F14: 9745 | H14: Shorter holds punish capex and reward efficiency. Ranking does not flip, but the absolute number roughly doubles at 5 years.
B15: 3 | C15: =(Compare!$C$30+Compare!$C$25*Inputs!$C$10*IF(Inputs!$C$11=0,3,((1+Inputs!$C$11)^3-1)/Inputs!$C$11)-Inputs!$C$19)/(Compare!$C$20*Inputs!$C$8*3) -> 5.2947837 | D15: =(Compare!$D$30+Compare!$D$25*Inputs!$C$10*IF(Inputs!$C$11=0,3,((1+Inputs!$C$11)^3-1)/Inputs!$C$11)-Inputs!$C$19)/(Compare!$D$20*Inputs!$C$8*3) -> 6.8897839 | E15: =(Compare!$E$30+Compare!$E$25*Inputs!$C$10*IF(Inputs!$C$11=0,3,((1+Inputs!$C$11)^3-1)/Inputs!$C$11)-Inputs!$C$19)/(Compare!$E$20*Inputs!$C$8*3) -> 6.3049634 | F15: =(Compare!$F$30+Compare!$F$25*Inputs!$C$10*IF(Inputs!$C$11=0,3,((1+Inputs!$C$11)^3-1)/Inputs!$C$11)-Inputs!$C$19)/(Compare!$F$20*Inputs!$C$8*3) -> 7.0573998
B16: 5 | C16: =(Compare!$C$30+Compare!$C$25*Inputs!$C$10*IF(Inputs!$C$11=0,5,((1+Inputs!$C$11)^5-1)/Inputs!$C$11)-Inputs!$C$19)/(Compare!$C$20*Inputs!$C$8*5) -> 3.433464 | D16: =(Compare!$D$30+Compare!$D$25*Inputs!$C$10*IF(Inputs!$C$11=0,5,((1+Inputs!$C$11)^5-1)/Inputs!$C$11)-Inputs!$C$19)/(Compare!$D$20*Inputs!$C$8*5) -> 4.3711007 | E16: =(Compare!$E$30+Compare!$E$25*Inputs!$C$10*IF(Inputs!$C$11=0,5,((1+Inputs!$C$11)^5-1)/Inputs!$C$11)-Inputs!$C$19)/(Compare!$E$20*Inputs!$C$8*5) -> 4.1190772 | F16: =(Compare!$F$30+Compare!$F$25*Inputs!$C$10*IF(Inputs!$C$11=0,5,((1+Inputs!$C$11)^5-1)/Inputs!$C$11)-Inputs!$C$19)/(Compare!$F$20*Inputs!$C$8*5) -> 4.5011967
B17: 7 | C17: =(Compare!$C$30+Compare!$C$25*Inputs!$C$10*IF(Inputs!$C$11=0,7,((1+Inputs!$C$11)^7-1)/Inputs!$C$11)-Inputs!$C$19)/(Compare!$C$20*Inputs!$C$8*7) -> 2.6357555 | D17: =(Compare!$D$30+Compare!$D$25*Inputs!$C$10*IF(Inputs!$C$11=0,7,((1+Inputs!$C$11)^7-1)/Inputs!$C$11)-Inputs!$C$19)/(Compare!$D$20*Inputs!$C$8*7) -> 3.291665 | E17: =(Compare!$E$30+Compare!$E$25*Inputs!$C$10*IF(Inputs!$C$11=0,7,((1+Inputs!$C$11)^7-1)/Inputs!$C$11)-Inputs!$C$19)/(Compare!$E$20*Inputs!$C$8*7) -> 3.1822689 | F17: =(Compare!$F$30+Compare!$F$25*Inputs!$C$10*IF(Inputs!$C$11=0,7,((1+Inputs!$C$11)^7-1)/Inputs!$C$11)-Inputs!$C$19)/(Compare!$F$20*Inputs!$C$8*7) -> 3.4056811
B18: 10 | C18: =(Compare!$C$30+Compare!$C$25*Inputs!$C$10*IF(Inputs!$C$11=0,10,((1+Inputs!$C$11)^10-1)/Inputs!$C$11)-Inputs!$C$19)/(Compare!$C$20*Inputs!$C$8*10) -> 2.0374742 | D18: =(Compare!$D$30+Compare!$D$25*Inputs!$C$10*IF(Inputs!$C$11=0,10,((1+Inputs!$C$11)^10-1)/Inputs!$C$11)-Inputs!$C$19)/(Compare!$D$20*Inputs!$C$8*10) -> 2.4820882 | E18: =(Compare!$E$30+Compare!$E$25*Inputs!$C$10*IF(Inputs!$C$11=0,10,((1+Inputs!$C$11)^10-1)/Inputs!$C$11)-Inputs!$C$19)/(Compare!$E$20*Inputs!$C$8*10) -> 2.4796626 | F18: =(Compare!$F$30+Compare!$F$25*Inputs!$C$10*IF(Inputs!$C$11=0,10,((1+Inputs!$C$11)^10-1)/Inputs!$C$11)-Inputs!$C$19)/(Compare!$F$20*Inputs!$C$8*10) -> 2.5840444
B19: 12 | C19: =(Compare!$C$30+Compare!$C$25*Inputs!$C$10*IF(Inputs!$C$11=0,12,((1+Inputs!$C$11)^12-1)/Inputs!$C$11)-Inputs!$C$19)/(Compare!$C$20*Inputs!$C$8*12) -> 1.8048093 | D19: =(Compare!$D$30+Compare!$D$25*Inputs!$C$10*IF(Inputs!$C$11=0,12,((1+Inputs!$C$11)^12-1)/Inputs!$C$11)-Inputs!$C$19)/(Compare!$D$20*Inputs!$C$8*12) -> 2.1672528 | E19: =(Compare!$E$30+Compare!$E$25*Inputs!$C$10*IF(Inputs!$C$11=0,12,((1+Inputs!$C$11)^12-1)/Inputs!$C$11)-Inputs!$C$19)/(Compare!$E$20*Inputs!$C$8*12) -> 2.2064268 | F19: =(Compare!$F$30+Compare!$F$25*Inputs!$C$10*IF(Inputs!$C$11=0,12,((1+Inputs!$C$11)^12-1)/Inputs!$C$11)-Inputs!$C$19)/(Compare!$F$20*Inputs!$C$8*12) -> 2.264519
B21: C. BREAKEVENS
B22: Question | C22: Answer | H22: Solved algebraically against the current winner.
B23: 9845 CPU price that ties the 9965 | C23: =Compare!$C$37*(Compare!$D$20*Inputs!$C$8*Inputs!$C$7)-Compare!$D$29-Compare!$D$25*Inputs!$C$10*Inputs!$C$33+Inputs!$C$19 -> 3683.798 | H23: The 9845 is the perf/watt champion. This is what it would have to cost to also be the value champion. Compare to its ~$9,684 street.
B24: 9745 CPU price that ties the 9965 | C24: =Compare!$C$37*(Compare!$F$20*Inputs!$C$8*Inputs!$C$7)-Compare!$F$29-Compare!$F$25*Inputs!$C$10*Inputs!$C$33+Inputs!$C$19 -> 640.31034 | H24: Against ~$7,200 street. A negative number means it cannot get there at any price.
B25: 9755 CPU price that ties the 9965 | C25: =Compare!$C$37*(Compare!$E$20*Inputs!$C$8*Inputs!$C$7)-Compare!$E$29-Compare!$E$25*Inputs!$C$10*Inputs!$C$33+Inputs!$C$19 -> 482.79597 | H25: Against ~$6,500 street.
B26: Energy as % of 10-yr TCO (winner) | C26: =INDEX(Compare!$C$39:$F$39, MATCH(MIN(Compare!$C$37:$F$37),Compare!$C$37:$F$37,0)) -> 0.31484297 | H26: If this is small, you are buying hardware, not electricity — and the cTDP argument matters less than the price argument.
B28: D. MEMORY — THE REAL LEVER
B29: $/GB | C29: Memory cost | D29: Winner Psi | H29: Memory is identical across candidates so it never changes the ranking — but it is the largest single number you control.
B30: 8 | C30: =Inputs!$C$22*Inputs!$C$23*8 -> 3072 | D30: =(INDEX(Compare!$C$33:$F$33,MATCH(MIN(Compare!$C$37:$F$37),Compare!$C$37:$F$37,0))+(Inputs!$C$22*Inputs!$C$23*8-Inputs!$C$26))/INDEX(Compare!$C$36:$F$36,MATCH(MIN(Compare!$C$37:$F$37),Compare!$C$37:$F$37,0)) -> 1.3864595
B31: 15 | C31: =Inputs!$C$22*Inputs!$C$23*15 -> 5760 | D31: =(INDEX(Compare!$C$33:$F$33,MATCH(MIN(Compare!$C$37:$F$37),Compare!$C$37:$F$37,0))+(Inputs!$C$22*Inputs!$C$23*15-Inputs!$C$26))/INDEX(Compare!$C$36:$F$36,MATCH(MIN(Compare!$C$37:$F$37),Compare!$C$37:$F$37,0)) -> 1.5509759
B32: 25 | C32: =Inputs!$C$22*Inputs!$C$23*25 -> 9600 | D32: =(INDEX(Compare!$C$33:$F$33,MATCH(MIN(Compare!$C$37:$F$37),Compare!$C$37:$F$37,0))+(Inputs!$C$22*Inputs!$C$23*25-Inputs!$C$26))/INDEX(Compare!$C$36:$F$36,MATCH(MIN(Compare!$C$37:$F$37),Compare!$C$37:$F$37,0)) -> 1.7859992
B33: 35.7 | C33: =Inputs!$C$22*Inputs!$C$23*35.7 -> 13708.8 | D33: =(INDEX(Compare!$C$33:$F$33,MATCH(MIN(Compare!$C$37:$F$37),Compare!$C$37:$F$37,0))+(Inputs!$C$22*Inputs!$C$23*35.7-Inputs!$C$26))/INDEX(Compare!$C$36:$F$36,MATCH(MIN(Compare!$C$37:$F$37),Compare!$C$37:$F$37,0)) -> 2.0374742
B34: 45 | C34: =Inputs!$C$22*Inputs!$C$23*45 -> 17280 | D34: =(INDEX(Compare!$C$33:$F$33,MATCH(MIN(Compare!$C$37:$F$37),Compare!$C$37:$F$37,0))+(Inputs!$C$22*Inputs!$C$23*45-Inputs!$C$26))/INDEX(Compare!$C$36:$F$36,MATCH(MIN(Compare!$C$37:$F$37),Compare!$C$37:$F$37,0)) -> 2.2560459
B35: Pre-shortage $/GB was roughly $8. Waiting for normalisation is worth more than any CPU decision on this sheet.

Sheet Rent Compare
B2: OWN vs RENT — SAME METRIC
B3: Hetzner repriced 15 June 2026. Cloud instances rose 128-205%; dedicated followed.
B5: Option | C5: SPECrate 1P | D5: $ / month | E5: $ / pt-year | F5: x vs owning
B6: YOUR NODE (winner) | C6: =INDEX(Compare!$C$20:$F$20, MATCH(MIN(Compare!$C$37:$F$37),Compare!$C$37:$F$37,0)) -> 1633.8802 | D6: =INDEX(Compare!$C$33:$F$33, MATCH(MIN(Compare!$C$37:$F$37),Compare!$C$37:$F$37,0))/(Inputs!$C$7*12) -> 277.41572 | E6: =MIN(Compare!$C$37:$F$37) -> 2.0374742 | F6: 1.00x | G6: Amortised all-in. Change the hold period on Inputs to see the 5-year figure.
B7: Hetzner AX162-1 | C7: 523 | D7: 722.1 | E7: =D7*12/C7 -> 16.56826 | F7: =E7/$E$6 -> 8.1317643 | G7: EPYC 9454P, 48 Zen 4 cores. Standard tier, excl. IPv4 and VAT, plus $359 setup. Launched at EUR 199/mo in Feb-2024.
B8: Hetzner AX162-1-LTD | C8: 523 | D8: 372.1 | E8: =D8*12/C8 -> 8.5376673 | F8: =E8/$E$6 -> 4.1903192 | G8: Same box, limited-supply tier. Availability is not guaranteed and cannot be counted on for fleet planning.
B10: Boxes needed to match your node | C10: =C6/C7 -> 3.1240538
B11: That fleet, per year | C11: =C10*D7*12 -> 27070.551 | G11: Compare to your entire hold-period TCO. One year of equivalent rental costs more than a decade of owning.
B13: WHAT RENTING BUYS THAT THIS MODEL DOES NOT PRICE
B14: Hardware replacement, redundant power, and someone else on call at 3am.
B15: The option to stop paying. Your capex is sunk on day one; a rental is cancellable monthly.
B16: No exposure to the DRAM market. Hetzner ate that risk and passed some of it through — you would eat all of it.
B17: Against that: dedicated is EU-only, which is irrelevant for hand-fed batch jobs but not for anything interactive.

Sheet Sources
B2: SOURCES & CONFIDENCE
B3: Every hardcoded number in this workbook. Checked August 2026.
B5: Figure | C5: Value | D5: Confidence | E5: Source
B6: 9965 2P SPECrate int_base | C6: 3,100-3,230 | D6: Measured | E6: spec.org vendor submissions: ASUS RS720A-E13 3,230; Kaytus KR1280V3 3,150; H3C R4950 G7 3,130; Gigabyte R183-Z93 3,100. Median 3,140 used.
B7: 9845 2P SPECrate int_base | C7: 2,620 | D7: Measured (n=1) | E7: spec.org, Dell PowerEdge M7725, Mar-2025. Only one published result — the thinnest evidence of the four.
B8: 9745 2P SPECrate int_base | C8: 2,290-2,400 | D8: Measured | E8: spec.org: Fujitsu RX2450 M2 2,290; Lenovo SR665 V3 2,300; Dell R6725 2,340; Dell R7725 2,400. Median 2,330 used.
B9: 9745 1P SPECrate int_base | C9: 1,170-1,270 | D9: Measured | E9: spec.org: Dell R6715 1,170; xFusion 2158H V8 1,230; ASUS RS520QA 1,270. Used only to calibrate sigma.
B10: 9755 2P SPECrate int_base | C10: 2,589 | D10: DERIVED | E10: No published SPECrate found. Back-solved from Phoronix: the 9745 hit ~90% of the 9755 across a 555-benchmark geomean. Treat as the softest number here.
B11: sigma (1P scaling) | C11: 0.5256 | D11: Calibrated | E11: 9745 1P median 1,230 / 9745 2P median 2,340. Applied identically to all four, so it does not affect the ranking.
B12: phi at 320W cTDP | C12: 0.98 | D12: Measured | E12: Phoronix, Mar-2026 (Gigabyte MZ33-AR1): the 9745 at 320W cTDP delivered ~98% of its 400W performance. Peak CPU draw was 379W at the 400W rating.
B13: phi at 450W on the 9965 | C13: 0.99 | D13: ESTIMATE | E13: Nobody published 450-vs-500 on the 9965. Extrapolated from the 9745 result, adjusted for the smaller cut (10% vs 20%). This is my number, not a measurement.
B14: 9965 street price | C14: ~$7,000 | D14: Current | E14: AMD 1kU cut from $14,813 to $11,988. US eBay new listings ~$6,995; TechRadar tracked sub-$6,000 new in Jun-2026. Volatile.
B15: 9845 street price | C15: $9,684 | D15: Current | E15: IT Creations, new, unlocked tray. AMD 1kU $11,411. Notably has NOT seen the discounting the 9965 did.
B16: 9755 street price | C16: ~$6,500 | D16: Current | E16: Phoronix noted ~$7,200 at major retailers Mar-2026; an eBay dealer listed $6,169.
... B25: EPYC 9454P 1P SPECrate | C25: 523 | D25: Measured | E25: spec.org, Dell PowerEdge R6615, Nov-2023. The CPU in the Hetzner AX162.
